pdm_packer-0.8.2.dist-info/METADATA
pdm_packer-0.8.2.dist-info/WHEEL
pdm_packer-0.8.2.dist-info/entry_points.txt
pdm_packer-0.8.2.dist-info/licenses/LICENSE
pdm_packer/__init__.py
pdm_packer/_compile_source.py
pdm_packer/command.py
pdm_packer/env.py
pdm_packer-0.8.2.dist-info/RECORD
