Metadata-Version: 2.1
Name: pdm-packer
Version: 0.8.2
Summary: A PDM plugin that packs your packages into a zipapp
Author-Email: Frost Ming <mianghong@gmail.com>
License: MIT
Classifier: Development Status :: 3 - Alpha
Classifier: Programming Language :: Python :: 3
Project-URL: Repository, https://github.com/frostming/pdm-packer
Project-URL: Homepage, https://github.com/frostming/pdm-packer
Requires-Python: >=3.9
Requires-Dist: distlib>=0.3.4; sys_platform == "win32"
